request_security/__init__.py
request_security/middleware.py
request_security/settings.py
request_security/signature.py
request_security/utils.py
django_request_security-0.0.5.dist-info/METADATA
django_request_security-0.0.5.dist-info/WHEEL
django_request_security-0.0.5.dist-info/top_level.txt
django_request_security-0.0.5.dist-info/RECORD
