Metadata-Version: 2.1
Name: django-request-security
Version: 0.0.5
Summary: third-party libraries that enhance the security of the Django API
Home-page: https://github.com/lucatisfun/django-request-security
Author: liyao
Author-email: liyao2598330@126.com
License: UNKNOWN
Platform: UNKNOWN
Classifier: Programming Language :: Python :: 3
Classifier: License :: OSI Approved :: MIT License
Requires-Python: >=3
